mitoscripts/__init__.py
mitoscripts/mitodata.py
mitoscripts/mitographer.py
mitoscripts/mitopca.py
src/__init__.py
src/mitoscripts/__init__.py
src/mitoscripts/mitodata.py
src/mitoscripts/mitographer.py
src/mitoscripts/mitopca.py
mitoscripts-1.1.0.dist-info/METADATA
mitoscripts-1.1.0.dist-info/WHEEL
mitoscripts-1.1.0.dist-info/top_level.txt
mitoscripts-1.1.0.dist-info/RECORD
