Metadata-Version: 2.1
Name: mitoscripts
Version: 1.1.0
Summary: To assist in quantifying mitochondrial morphology
Home-page: https://github.com/granthussey/MitoScripts
Author: Grant Hussey
Author-email: grant.hussey@nyulangone.org
License: UNKNOWN
Platform: UNKNOWN
Classifier: Programming Language :: Python :: 3
Classifier: License :: OSI Approved :: MIT License
Classifier: Operating System :: OS Independent
Requires-Python: >=3.6
Requires-Dist: numpy
Requires-Dist: pandas
Requires-Dist: scikit-learn
Requires-Dist: python-igraph
Requires-Dist: matplotlib
Requires-Dist: seaborn
